sturgmapdemo/__init__.py
sturgmapdemo/common.py
sturgmapdemo/sturgmapdemo.py
sturgmapdemo-0.0.1.dist-info/LICENSE
sturgmapdemo-0.0.1.dist-info/METADATA
sturgmapdemo-0.0.1.dist-info/WHEEL
sturgmapdemo-0.0.1.dist-info/entry_points.txt
sturgmapdemo-0.0.1.dist-info/top_level.txt
sturgmapdemo-0.0.1.dist-info/RECORD
